templated_setup
