Metadata-Version: 2.1
Name: templated_setup
Version: 0.9977
Summary: A quick and easy replacement for some `setup.py` implementations.
Author: matrikater (Joel Watson)
Author-email: administraitor@matriko.xyz
License-File: LICENCE
Requires-Dist: setuptools
Requires-Dist: twine
